ObjTerm/__init__.py
PyObjTerm/__init__.py
ObjTerm-0.9.dist-info/LICENCE
ObjTerm-0.9.dist-info/METADATA
ObjTerm-0.9.dist-info/WHEEL
ObjTerm-0.9.dist-info/top_level.txt
ObjTerm-0.9.dist-info/RECORD
