Metadata-Version: 2.1
Name: ObjTerm
Version: 0.9
Summary: A interactive terminal to call methods on python objects
Home-page: https://gitlab.com/craigukaea/objterm
Author: Craig Hickman
Author-email: craig.hickman@ukaea.uk
License: UNKNOWN
Platform: UNKNOWN
Classifier: Programming Language :: Python :: 3
Classifier: License :: OSI Approved :: MIT License
Classifier: Operating System :: OS Independent
Requires-Dist: PyInquirer
